rclco/__init__.py
rclco/_version.py
rclco/apis.py
rclco/databases.py
rclco/sharepoint.py
rclco/storage.py
rclco/config/__init__.py
rclco/config/settings.py
rclco/config/vault.py
rclco/connectors/__init__.py
rclco/connectors/base.py
rclco/connectors/api/__init__.py
rclco/connectors/api/client.py
rclco/connectors/database/__init__.py
rclco/connectors/database/azure_sql.py
rclco/connectors/database/base.py
rclco/connectors/database/postgres.py
rclco/connectors/microsoft/__init__.py
rclco/connectors/microsoft/sharepoint.py
rclco/connectors/storage/__init__.py
rclco/connectors/storage/azure_blob.py
rclco/core/__init__.py
rclco/core/exceptions.py
rclco/core/logging.py
rclco/core/types.py
rclco/data/__init__.py
rclco/data/demographics/__init__.py
rclco/data/demographics/esri.py
rclco/utils/__init__.py
rclco/utils/retry.py
rclco/viz/__init__.py
rclco/viz/_charts.py
rclco/viz/_colors.py
rclco/viz/_maps.py
rclco-0.2.2.dist-info/METADATA
rclco-0.2.2.dist-info/WHEEL
rclco-0.2.2.dist-info/RECORD
