Metadata-Version: 2.4
Name: rclco
Version: 0.2.2
Summary: RCLCO Python library - Core data connectivity for databases, APIs, storage, and SharePoint
Author-email: scott-stoltzman-consulting <scott@stoltzmanconsulting.com>
Requires-Python: >=3.10
Requires-Dist: azure-identity>=1.15
Requires-Dist: azure-keyvault-secrets>=4.8
Requires-Dist: azure-storage-blob>=12.0
Requires-Dist: folium>=0.14
Requires-Dist: geopandas>=1.1.2
Requires-Dist: httpx>=0.27
Requires-Dist: mapclassify>=2.5
Requires-Dist: matplotlib>=3.7
Requires-Dist: msal>=1.28
Requires-Dist: office365-rest-python-client>=2.5
Requires-Dist: polars>=1.0
Requires-Dist: psycopg[binary]>=3.1
Requires-Dist: pyarrow>=23.0.0
Requires-Dist: pygris>=0.2.1
Requires-Dist: pyodbc>=5.0
Provides-Extra: dev
Requires-Dist: mypy>=1.9; extra == 'dev'
Requires-Dist: pytest-asyncio>=0.23; extra == 'dev'
Requires-Dist: pytest>=8.0; extra == 'dev'
Requires-Dist: ruff>=0.3; extra == 'dev'
